pdf2index/__about__.py
pdf2index/__init__.py
pdf2index/__main__.py
pdf2index/keywords.py
pdf2index/pdf.py
pdf2index-0.1.0.dist-info/METADATA
pdf2index-0.1.0.dist-info/WHEEL
pdf2index-0.1.0.dist-info/entry_points.txt
pdf2index-0.1.0.dist-info/licenses/LICENSE.txt
pdf2index-0.1.0.dist-info/RECORD
