Metadata-Version: 2.3
Name: pdf2index
Version: 0.1.0
Project-URL: Documentation, https://gitlab.com/philipp.herkert/pdf2index
Project-URL: Issues, https://gitlab.com/philipp.herkert/pdf2index/-/issues
Project-URL: Source, https://gitlab.com/philipp.herkert/pdf2index
Author: Philipp Herkert
License-Expression: MIT
License-File: LICENSE.txt
Classifier: Development Status :: 4 - Beta
Classifier: Programming Language :: Python
Classifier: Programming Language :: Python :: 3.12
Classifier: Programming Language :: Python :: 3.13
Classifier: Programming Language :: Python :: 3.14
Classifier: Programming Language :: Python :: Implementation :: CPython
Classifier: Programming Language :: Python :: Implementation :: PyPy
Requires-Python: >=3.12
Requires-Dist: keybert
Requires-Dist: pypdfium2
Requires-Dist: torch
Requires-Dist: torchaudio
Requires-Dist: torchvision
Requires-Dist: typer
